<?xml version="1.0" encoding="UTF-8" standalone="no"?>
<geonames style="FULL">
<totalResultsCount>36</totalResultsCount>
<geoname>
<toponymName>Washington County</toponymName>
<name>Washington County</name>
<lat>30.61059</lat>
<lng>-85.66533</lng>
<geonameId>4177485</geonameId>
<countryCode>US</countryCode>
<countryName>United States</countryName>
<fcl>A</fcl>
<fcode>ADM2</fcode>
<fclName>country, state, region,...</fclName>
<fcodeName>second-order administrative division</fcodeName>
<population>24896</population>
<alternateNames>Comte de Washington,Comté de Washington</alternateNames>
<elevation>45</elevation>
<continentCode>NA</continentCode>
<adminCode1 ISO3166-2="FL">FL</adminCode1>
<adminName1>Florida</adminName1>
<adminCode2>133</adminCode2>
<adminName2>Washington County</adminName2>
<alternateName lang="fr">Comté de Washington</alternateName>
<alternateName lang="link">http://en.wikipedia.org/wiki/Washington_County%2C_Florida</alternateName>
<timezone dstOffset="-5.0" gmtOffset="-6.0">America/Chicago</timezone>
<bbox>
<west>-85.99279</west>
<north>30.83052</north>
<east>-85.433</east>
<south>30.38927</south>
</bbox>
<score>60.63048553466797</score>
</geoname>
<geoname>
<toponymName>Washington County</toponymName>
<name>Washington County</name>
<lat>32.96954</lat>
<lng>-82.7959</lng>
<geonameId>4229557</geonameId>
<countryCode>US</countryCode>
<countryName>United States</countryName>
<fcl>A</fcl>
<fcode>ADM2</fcode>
<fclName>country, state, region,...</fclName>
<fcodeName>second-order administrative division</fcodeName>
<population>21187</population>
<alternateNames>Comte de Washington,Comté de Washington</alternateNames>
<elevation>136</elevation>
<continentCode>NA</continentCode>
<adminCode1 ISO3166-2="GA">GA</adminCode1>
<adminName1>Georgia</adminName1>
<adminCode2>303</adminCode2>
<adminName2>Washington County</adminName2>
<alternateName lang="fr">Comté de Washington</alternateName>
<alternateName lang="link">http://en.wikipedia.org/wiki/Washington_County%2C_Georgia</alternateName>
<timezone dstOffset="-4.0" gmtOffset="-5.0">America/New_York</timezone>
<bbox>
<west>-83.07352</west>
<north>33.23822</north>
<east>-82.5108</east>
<south>32.75911</south>
</bbox>
<score>60.63048553466797</score>
</geoname>
<geoname>
<toponymName>Washington County</toponymName>
<name>Washington County</name>
<lat>37.75338</lat>
<lng>-85.17475</lng>
<geonameId>4312745</geonameId>
<countryCode>US</countryCode>
<countryName>United States</countryName>
<fcl>A</fcl>
<fcode>ADM2</fcode>
<fclName>country, state, region,...</fclName>
<fcodeName>second-order administrative division</fcodeName>
<population>11717</population>
<alternateNames>Comte de Washington,Comté de Washington</alternateNames>
<elevation>241</elevation>
<continentCode>NA</continentCode>
<adminCode1 ISO3166-2="KY">KY</adminCode1>
<adminName1>Kentucky</adminName1>
<adminCode2>229</adminCode2>
<adminName2>Washington County</adminName2>
<alternateName lang="fr">Comté de Washington</alternateName>
<alternateName lang="link">http://en.wikipedia.org/wiki/Washington_County%2C_Kentucky</alternateName>
<timezone dstOffset="-4.0" gmtOffset="-5.0">America/New_York</timezone>
<bbox>
<west>-85.40162</west>
<north>37.91566</north>
<east>-85.00043</east>
<south>37.63089</south>
</bbox>
<score>60.63048553466797</score>
</geoname>
<geoname>
<toponymName>Washington County</toponymName>
<name>Washington County</name>
<lat>37.96168</lat>
<lng>-90.87742</lng>
<geonameId>4413630</geonameId>
<countryCode>US</countryCode>
<countryName>United States</countryName>
<fcl>A</fcl>
<fcode>ADM2</fcode>
<fclName>country, state, region,...</fclName>
<fcodeName>second-order administrative division</fcodeName>
<population>25195</population>
<alternateNames>Comte de Washington,Comté de Washington</alternateNames>
<elevation>292</elevation>
<continentCode>NA</continentCode>
<adminCode1 ISO3166-2="MO">MO</adminCode1>
<adminName1>Missouri</adminName1>
<adminCode2>221</adminCode2>
<adminName2>Washington County</adminName2>
<alternateName lang="fr">Comté de Washington</alternateName>
<alternateName lang="link">http://en.wikipedia.org/wiki/Washington_County%2C_Missouri</alternateName>
<timezone dstOffset="-5.0" gmtOffset="-6.0">America/Chicago</timezone>
<bbox>
<west>-91.1004</west>
<north>38.21114</north>
<east>-90.63962</east>
<south>37.73619</south>
</bbox>
<score>60.63048553466797</score>
</geoname>
<geoname>
<toponymName>Washington County</toponymName>
<name>Washington County</name>
<lat>33.2837</lat>
<lng>-90.94745</lng>
<geonameId>4450315</geonameId>
<countryCode>US</countryCode>
<countryName>United States</countryName>
<fcl>A</fcl>
<fcode>ADM2</fcode>
<fclName>country, state, region,...</fclName>
<fcodeName>second-order administrative division</fcodeName>
<population>51137</population>
<alternateNames>Comte de Washington,Comté de Washington</alternateNames>
<elevation>34</elevation>
<continentCode>NA</continentCode>
<adminCode1 ISO3166-2="MS">MS</adminCode1>
<adminName1>Mississippi</adminName1>
<adminCode2>151</adminCode2>
<adminName2>Washington County</adminName2>
<alternateName lang="fr">Comté de Washington</alternateName>
<alternateName lang="link">http://en.wikipedia.org/wiki/Washington_County%2C_Mississippi</alternateName>
<timezone dstOffset="-5.0" gmtOffset="-6.0">America/Chicago</timezone>
<bbox>
<west>-91.23486</west>
<north>33.52929</north>
<east>-90.67877</east>
<south>33.00763</south>
</bbox>
<score>60.63048553466797</score>
</geoname>
<geoname>
<toponymName>Washington County</toponymName>
<name>Washington County</name>
<lat>35.83887</lat>
<lng>-76.56868</lng>
<geonameId>4497673</geonameId>
<countryCode>US</countryCode>
<countryName>United States</countryName>
<fcl>A</fcl>
<fcode>ADM2</fcode>
<fclName>country, state, region,...</fclName>
<fcodeName>second-order administrative division</fcodeName>
<population>13228</population>
<alternateNames>Comte de Washington,Comté de Washington</alternateNames>
<elevation>3</elevation>
<continentCode>NA</continentCode>
<adminCode1 ISO3166-2="NC">NC</adminCode1>
<adminName1>North Carolina</adminName1>
<adminCode2>187</adminCode2>
<adminName2>Washington County</adminName2>
<alternateName lang="fr">Comté de Washington</alternateName>
<alternateName lang="link">http://en.wikipedia.org/wiki/Washington_County%2C_North_Carolina</alternateName>
<timezone dstOffset="-4.0" gmtOffset="-5.0">America/New_York</timezone>
<bbox>
<west>-76.83924</west>
<north>35.98314</north>
<east>-76.35199</east>
<south>35.6977</south>
</bbox>
<score>60.63048553466797</score>
</geoname>
<geoname>
<toponymName>Washington County</toponymName>
<name>Washington County</name>
<lat>39.45532</lat>
<lng>-81.49525</lng>
<geonameId>4527654</geonameId>
<countryCode>US</countryCode>
<countryName>United States</countryName>
<fcl>A</fcl>
<fcode>ADM2</fcode>
<fclName>country, state, region,...</fclName>
<fcodeName>second-order administrative division</fcodeName>
<population>61778</population>
<alternateNames>Comte de Washington,Comté de Washington</alternateNames>
<elevation>231</elevation>
<continentCode>NA</continentCode>
<adminCode1 ISO3166-2="OH">OH</adminCode1>
<adminName1>Ohio</adminName1>
<adminCode2>167</adminCode2>
<adminName2>Washington County</adminName2>
<alternateName lang="fr">Comté de Washington</alternateName>
<alternateName lang="link">http://en.wikipedia.org/wiki/Washington_County%2C_Ohio</alternateName>
<timezone dstOffset="-4.0" gmtOffset="-5.0">America/New_York</timezone>
<bbox>
<west>-81.85347</west>
<north>39.64566</north>
<east>-81.03419</east>
<south>39.2159</south>
</bbox>
<score>60.63048553466797</score>
</geoname>
<geoname>
<toponymName>Washington County</toponymName>
<name>Washington County</name>
<lat>36.71524</lat>
<lng>-95.90437</lng>
<geonameId>4554708</geonameId>
<countryCode>US</countryCode>
<countryName>United States</countryName>
<fcl>A</fcl>
<fcode>ADM2</fcode>
<fclName>country, state, region,...</fclName>
<fcodeName>second-order administrative division</fcodeName>
<population>50976</population>
<alternateNames>Comte de Washington,Comté de Washington</alternateNames>
<elevation>238</elevation>
<continentCode>NA</continentCode>
<adminCode1 ISO3166-2="OK">OK</adminCode1>
<adminName1>Oklahoma</adminName1>
<adminCode2>147</adminCode2>
<adminName2>Washington County</adminName2>
<alternateName lang="fr">Comté de Washington</alternateName>
<alternateName lang="link">http://en.wikipedia.org/wiki/Washington_County%2C_Oklahoma</alternateName>
<timezone dstOffset="-5.0" gmtOffset="-6.0">America/Chicago</timezone>
<bbox>
<west>-96.00037</west>
<north>37.00047</north>
<east>-95.78843</east>
<south>36.42484</south>
</bbox>
<score>60.63048553466797</score>
</geoname>
<geoname>
<toponymName>Washington County</toponymName>
<name>Washington County</name>
<lat>36.2933</lat>
<lng>-82.49743</lng>
<geonameId>4665975</geonameId>
<countryCode>US</countryCode>
<countryName>United States</countryName>
<fcl>A</fcl>
<fcode>ADM2</fcode>
<fclName>country, state, region,...</fclName>
<fcodeName>second-order administrative division</fcodeName>
<population>122979</population>
<alternateNames>Comte de Washington,Comté de Washington</alternateNames>
<elevation>530</elevation>
<continentCode>NA</continentCode>
<adminCode1 ISO3166-2="TN">TN</adminCode1>
<adminName1>Tennessee</adminName1>
<adminCode2>179</adminCode2>
<adminName2>Washington County</adminName2>
<alternateName lang="fr">Comté de Washington</alternateName>
<alternateName lang="link">http://en.wikipedia.org/wiki/Washington_County%2C_Tennessee</alternateName>
<timezone dstOffset="-4.0" gmtOffset="-5.0">America/New_York</timezone>
<bbox>
<west>-82.70278</west>
<north>36.44479</north>
<east>-82.30013</east>
<south>36.09705</south>
</bbox>
<score>60.63048553466797</score>
</geoname>
<geoname>
<toponymName>Washington County</toponymName>
<name>Washington County</name>
<lat>30.21453</lat>
<lng>-96.40344</lng>
<geonameId>4740157</geonameId>
<countryCode>US</countryCode>
<countryName>United States</countryName>
<fcl>A</fcl>
<fcode>ADM2</fcode>
<fclName>country, state, region,...</fclName>
<fcodeName>second-order administrative division</fcodeName>
<population>33718</population>
<alternateNames>Comte de Washington,Comté de Washington</alternateNames>
<elevation>72</elevation>
<continentCode>NA</continentCode>
<adminCode1 ISO3166-2="TX">TX</adminCode1>
<adminName1>Texas</adminName1>
<adminCode2>477</adminCode2>
<adminName2>Washington County</adminName2>
<alternateName lang="fr">Comté de Washington</alternateName>
<alternateName lang="link">http://en.wikipedia.org/wiki/Washington_County%2C_Texas</alternateName>
<timezone dstOffset="-5.0" gmtOffset="-6.0">America/Chicago</timezone>
<bbox>
<west>-96.79316</west>
<north>30.39692</north>
<east>-96.08218</east>
<south>30.04909</south>
</bbox>
<score>60.63048553466797</score>
</geoname>
</geonames>
