<?xml version="1.0" encoding="UTF-8" standalone="no"?>
<geonames style="FULL">
<totalResultsCount>4</totalResultsCount>
<geoname>
<toponymName>Hyacinth</toponymName>
<name>Hyacinth</name>
<lat>37.99069</lat>
<lng>-76.59023</lng>
<geonameId>4765528</geonameId>
<countryCode>US</countryCode>
<countryName>United States</countryName>
<fcl>P</fcl>
<fcode>PPL</fcode>
<fclName>city, village,...</fclName>
<fcodeName>populated place</fcodeName>
<population/>
<alternateNames/>
<elevation>29</elevation>
<continentCode>NA</continentCode>
<adminCode1 ISO3166-2="VA">VA</adminCode1>
<adminName1>Virginia</adminName1>
<adminCode2>133</adminCode2>
<adminName2>Northumberland County</adminName2>
<alternateName lang="link">http://en.wikipedia.org/wiki/Hyacinth%2C_Virginia</alternateName>
<timezone dstOffset="-4.0" gmtOffset="-5.0">America/New_York</timezone>
<bbox>
<west>-76.60165</west>
<north>37.99968</north>
<east>-76.57882</east>
<south>37.98169</south>
</bbox>
<score>64.92164611816406</score>
</geoname>
<geoname>
<toponymName>Hyacinthe</toponymName>
<name>Hyacinthe</name>
<lat>18.36667</lat>
<lng>-73.01667</lng>
<geonameId>3723821</geonameId>
<countryCode>HT</countryCode>
<countryName>Haiti</countryName>
<fcl>P</fcl>
<fcode>PPL</fcode>
<fclName>city, village,...</fclName>
<fcodeName>populated place</fcodeName>
<population/>
<alternateNames/>
<elevation/>
<continentCode>NA</continentCode>
<adminCode1 ISO3166-2="GA">14</adminCode1>
<adminName1>GrandʼAnse</adminName1>
<adminCode2/>
<adminName2/>
<timezone dstOffset="-4.0" gmtOffset="-5.0">America/Port-au-Prince</timezone>
<bbox>
<west>-73.02614</west>
<north>18.37566</north>
<east>-73.00719</east>
<south>18.35767</south>
</bbox>
<score>14.876008033752441</score>
</geoname>
<geoname>
<toponymName>Hyacinthe</toponymName>
<name>Hyacinthe</name>
<lat>18.36667</lat>
<lng>-72.98333</lng>
<geonameId>3723822</geonameId>
<countryCode>HT</countryCode>
<countryName>Haiti</countryName>
<fcl>P</fcl>
<fcode>PPL</fcode>
<fclName>city, village,...</fclName>
<fcodeName>populated place</fcodeName>
<population/>
<alternateNames/>
<elevation/>
<continentCode>NA</continentCode>
<adminCode1 ISO3166-2="OU">11</adminCode1>
<adminName1>Ouest</adminName1>
<adminCode2/>
<adminName2/>
<timezone dstOffset="-4.0" gmtOffset="-5.0">America/Port-au-Prince</timezone>
<bbox>
<west>-72.99281</west>
<north>18.37566</north>
<east>-72.97386</east>
<south>18.35767</south>
</bbox>
<score>14.876008033752441</score>
</geoname>
<geoname>
<toponymName>Hyacinthe</toponymName>
<name>Hyacinthe</name>
<lat>14.65</lat>
<lng>-60.9</lng>
<geonameId>3570567</geonameId>
<countryCode>MQ</countryCode>
<countryName>Martinique</countryName>
<fcl>P</fcl>
<fcode>PPLL</fcode>
<fclName>city, village,...</fclName>
<fcodeName>populated locality</fcodeName>
<population/>
<alternateNames/>
<elevation/>
<continentCode>NA</continentCode>
<adminCode1>MQ</adminCode1>
<adminName1>Martinique</adminName1>
<adminCode2/>
<adminName2/>
<timezone dstOffset="-4.0" gmtOffset="-4.0">America/Martinique</timezone>
<bbox>
<west>-60.90093</west>
<north>14.6509</north>
<east>-60.89907</east>
<south>14.6491</south>
</bbox>
<score>9.297505378723145</score>
</geoname>
</geonames>
