<?xml version="1.0" encoding="UTF-8" standalone="no"?>
<geonames style="FULL">
<totalResultsCount>1</totalResultsCount>
<geoname>
<toponymName>Jessamine County</toponymName>
<name>Jessamine County</name>
<lat>37.87203</lat>
<lng>-84.58093</lng>
<geonameId>4296292</geonameId>
<countryCode>US</countryCode>
<countryName>United States</countryName>
<fcl>A</fcl>
<fcode>ADM2</fcode>
<fclName>country, state, region,...</fclName>
<fcodeName>second-order administrative division</fcodeName>
<population>48586</population>
<alternateNames>Comte de Jessamine,Comté de Jessamine</alternateNames>
<elevation>283</elevation>
<continentCode>NA</continentCode>
<adminCode1 ISO3166-2="KY">KY</adminCode1>
<adminName1>Kentucky</adminName1>
<adminCode2>113</adminCode2>
<adminName2>Jessamine County</adminName2>
<alternateName lang="fr">Comté de Jessamine</alternateName>
<alternateName lang="link">http://en.wikipedia.org/wiki/Jessamine_County%2C_Kentucky</alternateName>
<timezone dstOffset="-4.0" gmtOffset="-5.0">America/New_York</timezone>
<bbox>
<west>-84.72446</west>
<north>38.00356</north>
<east>-84.43423</east>
<south>37.72869</south>
</bbox>
<score>80.47520446777344</score>
</geoname>
</geonames>
