<?xml version="1.0" encoding="UTF-8" standalone="no"?>
<geonames style="FULL">
<totalResultsCount>36</totalResultsCount>
<geoname>
<toponymName>Låttern</toponymName>
<name>Låttern</name>
<lat>59.08333</lat>
<lng>16.03333</lng>
<geonameId>2696839</geonameId>
<countryCode>SE</countryCode>
<countryName>Sweden</countryName>
<fcl>H</fcl>
<fcode>LK</fcode>
<fclName>stream, lake, ...</fclName>
<fcodeName>lake</fcodeName>
<population/>
<alternateNames/>
<elevation/>
<continentCode>EU</continentCode>
<adminCode1 ISO3166-2="D">18</adminCode1>
<adminName1>Södermanland</adminName1>
<adminCode2/>
<adminName2/>
<timezone dstOffset="2.0" gmtOffset="1.0">Europe/Stockholm</timezone>
<score>28.142139434814453</score>
</geoname>
<geoname>
<toponymName>Lauter</toponymName>
<name>Lauter</name>
<lat>50.56264</lat>
<lng>12.73514</lng>
<geonameId>2879964</geonameId>
<countryCode>DE</countryCode>
<countryName>Germany</countryName>
<fcl>P</fcl>
<fcode>PPL</fcode>
<fclName>city, village,...</fclName>
<fcodeName>populated place</fcodeName>
<population>5028</population>
<alternateNames>Lauter</alternateNames>
<elevation/>
<continentCode>EU</continentCode>
<adminCode1 ISO3166-2="SN">13</adminCode1>
<adminName1>Saxony</adminName1>
<adminCode2/>
<adminName2/>
<alternateName lang="link">http://en.wikipedia.org/wiki/Lauter%2C_Saxony</alternateName>
<alternateName lang="unlc">TUR</alternateName>
<timezone dstOffset="2.0" gmtOffset="1.0">Europe/Berlin</timezone>
<bbox>
<west>12.72097</west>
<north>50.57164</north>
<east>12.7493</east>
<south>50.55365</south>
</bbox>
<score>22.895355224609375</score>
</geoname>
<geoname>
<toponymName>Lattes</toponymName>
<name>Lattes</name>
<lat>43.56752</lat>
<lng>3.9046</lng>
<geonameId>3006121</geonameId>
<countryCode>FR</countryCode>
<countryName>France</countryName>
<fcl>P</fcl>
<fcode>PPL</fcode>
<fclName>city, village,...</fclName>
<fcodeName>populated place</fcodeName>
<population>17390</population>
<alternateNames>Lattes</alternateNames>
<elevation/>
<continentCode>EU</continentCode>
<adminCode1 ISO3166-2="K">A9</adminCode1>
<adminName1>Languedoc-Roussillon</adminName1>
<adminCode2>34</adminCode2>
<adminName2>Hérault</adminName2>
<adminCode3>343</adminCode3>
<adminName3>Arrondissement of Montpellier</adminName3>
<adminCode4>34129</adminCode4>
<adminName4>Lattes</adminName4>
<alternateName lang="post">34970</alternateName>
<alternateName lang="unlc">LWT</alternateName>
<timezone dstOffset="2.0" gmtOffset="1.0">Europe/Paris</timezone>
<bbox>
<west>3.88138</west>
<north>43.58435</north>
<east>3.92783</east>
<south>43.5507</south>
</bbox>
<score>18.987062454223633</score>
</geoname>
<geoname>
<toponymName>Latteri</toponymName>
<name>Latteri</name>
<lat>12.97119</lat>
<lng>79.06853</lng>
<geonameId>1265016</geonameId>
<countryCode>IN</countryCode>
<countryName>India</countryName>
<fcl>P</fcl>
<fcode>PPL</fcode>
<fclName>city, village,...</fclName>
<fcodeName>populated place</fcodeName>
<population/>
<alternateNames/>
<elevation/>
<continentCode>AS</continentCode>
<adminCode1 ISO3166-2="TN">25</adminCode1>
<adminName1>Tamil Nādu</adminName1>
<adminCode2/>
<adminName2/>
<timezone dstOffset="5.5" gmtOffset="5.5">Asia/Kolkata</timezone>
<bbox>
<west>79.0593</west>
<north>12.98019</north>
<east>79.07776</east>
<south>12.9622</south>
</bbox>
<score>16.91434669494629</score>
</geoname>
<geoname>
<toponymName>Laiter</toponymName>
<name>Laiter</name>
<lat>47.93333</lat>
<lng>13.31667</lng>
<geonameId>2773122</geonameId>
<countryCode>AT</countryCode>
<countryName>Austria</countryName>
<fcl>P</fcl>
<fcode>PPL</fcode>
<fclName>city, village,...</fclName>
<fcodeName>populated place</fcodeName>
<population/>
<alternateNames/>
<elevation/>
<continentCode>EU</continentCode>
<adminCode1 ISO3166-2="4">04</adminCode1>
<adminName1>Upper Austria</adminName1>
<adminCode2/>
<adminName2/>
<timezone dstOffset="2.0" gmtOffset="1.0">Europe/Vienna</timezone>
<bbox>
<west>13.30324</west>
<north>47.94233</north>
<east>13.33009</east>
<south>47.92434</south>
</bbox>
<score>16.91434669494629</score>
</geoname>
<geoname>
<toponymName>Lapter</toponymName>
<name>Lapter</name>
<lat>-1.76</lat>
<lng>120.63611</lng>
<geonameId>1968618</geonameId>
<countryCode>ID</countryCode>
<countryName>Indonesia</countryName>
<fcl>P</fcl>
<fcode>PPL</fcode>
<fclName>city, village,...</fclName>
<fcodeName>populated place</fcodeName>
<population/>
<alternateNames/>
<elevation/>
<continentCode>AS</continentCode>
<adminCode1 ISO3166-2="ST">21</adminCode1>
<adminName1>Central Sulawesi</adminName1>
<adminCode2/>
<adminName2/>
<timezone dstOffset="8.0" gmtOffset="8.0">Asia/Makassar</timezone>
<bbox>
<west>120.62711</west>
<north>-1.75101</north>
<east>120.64511</east>
<south>-1.76899</south>
</bbox>
<score>16.081222534179688</score>
</geoname>
<geoname>
<toponymName>Lapter</toponymName>
<name>Lapter</name>
<lat>-1.87833</lat>
<lng>120.25722</lng>
<geonameId>1968667</geonameId>
<countryCode>ID</countryCode>
<countryName>Indonesia</countryName>
<fcl>P</fcl>
<fcode>PPL</fcode>
<fclName>city, village,...</fclName>
<fcodeName>populated place</fcodeName>
<population/>
<alternateNames/>
<elevation/>
<continentCode>AS</continentCode>
<adminCode1 ISO3166-2="ST">21</adminCode1>
<adminName1>Central Sulawesi</adminName1>
<adminCode2/>
<adminName2/>
<timezone dstOffset="8.0" gmtOffset="8.0">Asia/Makassar</timezone>
<bbox>
<west>120.24822</west>
<north>-1.86934</north>
<east>120.26622</east>
<south>-1.88733</south>
</bbox>
<score>16.081222534179688</score>
</geoname>
<geoname>
<toponymName>Lattes</toponymName>
<name>Lattes</name>
<lat>43.56889</lat>
<lng>3.90861</lng>
<geonameId>6432528</geonameId>
<countryCode>FR</countryCode>
<countryName>France</countryName>
<fcl>A</fcl>
<fcode>ADM4</fcode>
<fclName>country, state, region,...</fclName>
<fcodeName>fourth-order administrative division</fcodeName>
<population>15804</population>
<alternateNames/>
<elevation/>
<continentCode>EU</continentCode>
<adminCode1 ISO3166-2="K">A9</adminCode1>
<adminName1>Languedoc-Roussillon</adminName1>
<adminCode2>34</adminCode2>
<adminName2>Hérault</adminName2>
<adminCode3>343</adminCode3>
<adminName3>Arrondissement of Montpellier</adminName3>
<adminCode4>34129</adminCode4>
<adminName4>Lattes</adminName4>
<alternateName lang="link">http://en.wikipedia.org/wiki/Lattes%2C_H%C3%A9rault</alternateName>
<timezone dstOffset="2.0" gmtOffset="1.0">Europe/Paris</timezone>
<bbox>
<west>3.84751</west>
<north>43.59613</north>
<east>3.94805</east>
<south>43.53814</south>
</bbox>
<score>15.5028715133667</score>
</geoname>
<geoname>
<toponymName>Saint-Lattier</toponymName>
<name>Saint-Lattier</name>
<lat>45.08768</lat>
<lng>5.19261</lng>
<geonameId>2978974</geonameId>
<countryCode>FR</countryCode>
<countryName>France</countryName>
<fcl>P</fcl>
<fcode>PPL</fcode>
<fclName>city, village,...</fclName>
<fcodeName>populated place</fcodeName>
<population>1119</population>
<alternateNames>Lattier,Saint-Lattier</alternateNames>
<elevation/>
<continentCode>EU</continentCode>
<adminCode1 ISO3166-2="V">B9</adminCode1>
<adminName1>Rhône-Alpes</adminName1>
<adminCode2>38</adminCode2>
<adminName2>Isère</adminName2>
<adminCode3>381</adminCode3>
<adminName3>Arrondissement de Grenoble</adminName3>
<adminCode4>38410</adminCode4>
<adminName4>Saint-Lattier</adminName4>
<alternateName lang="fr_1793">Lattier</alternateName>
<alternateName lang="post">38840</alternateName>
<timezone dstOffset="2.0" gmtOffset="1.0">Europe/Paris</timezone>
<bbox>
<west>5.19133</west>
<north>45.08858</north>
<east>5.19388</east>
<south>45.08678</south>
</bbox>
<score>14.950312614440918</score>
</geoname>
<geoname>
<toponymName>Latten</toponymName>
<name>Latten</name>
<lat>47.83224</lat>
<lng>9.42805</lng>
<geonameId>2880339</geonameId>
<countryCode>DE</countryCode>
<countryName>Germany</countryName>
<fcl>P</fcl>
<fcode>PPL</fcode>
<fclName>city, village,...</fclName>
<fcodeName>populated place</fcodeName>
<population/>
<alternateNames/>
<elevation/>
<continentCode>EU</continentCode>
<adminCode1 ISO3166-2="BW">01</adminCode1>
<adminName1>Baden-Württemberg Region</adminName1>
<adminCode2>084</adminCode2>
<adminName2>Tübingen Region</adminName2>
<adminCode3>08436</adminCode3>
<adminName3>Landkreis Ravensburg</adminName3>
<adminCode4>08436083</adminCode4>
<adminName4>Wilhelmsdorf</adminName4>
<timezone dstOffset="2.0" gmtOffset="1.0">Europe/Berlin</timezone>
<bbox>
<west>9.41465</west>
<north>47.84123</north>
<east>9.44145</east>
<south>47.82324</south>
</bbox>
<score>14.152880668640137</score>
</geoname>
</geonames>
