<?xml version="1.0" encoding="UTF-8" standalone="no"?>
<geonames style="FULL">
<totalResultsCount>58</totalResultsCount>
<geoname>
<toponymName>Nortons</toponymName>
<name>Nortons</name>
<lat>44.66373</lat>
<lng>-123.70205</lng>
<geonameId>5743535</geonameId>
<countryCode>US</countryCode>
<countryName>United States</countryName>
<fcl>P</fcl>
<fcode>PPL</fcode>
<fclName>city, village,...</fclName>
<fcodeName>populated place</fcodeName>
<population/>
<alternateNames/>
<elevation>57</elevation>
<continentCode>NA</continentCode>
<adminCode1 ISO3166-2="OR">OR</adminCode1>
<adminName1>Oregon</adminName1>
<adminCode2>041</adminCode2>
<adminName2>Lincoln County</adminName2>
<alternateName lang="link">http://en.wikipedia.org/wiki/Nortons%2C_Oregon</alternateName>
<timezone dstOffset="-7.0" gmtOffset="-8.0">America/Los_Angeles</timezone>
<bbox>
<west>-123.7147</west>
<north>44.67272</north>
<east>-123.68941</east>
<south>44.65474</south>
</bbox>
<score>68.38423919677734</score>
</geoname>
<geoname>
<toponymName>Norton</toponymName>
<name>Norton</name>
<lat>-17.88333</lat>
<lng>30.7</lng>
<geonameId>884141</geonameId>
<countryCode>ZW</countryCode>
<countryName>Zimbabwe</countryName>
<fcl>P</fcl>
<fcode>PPL</fcode>
<fclName>city, village,...</fclName>
<fcodeName>populated place</fcodeName>
<population>52054</population>
<alternateNames>Norton,Нортон</alternateNames>
<elevation/>
<continentCode>AF</continentCode>
<adminCode1 ISO3166-2="MW">05</adminCode1>
<adminName1>Mashonaland West Province</adminName1>
<adminCode2/>
<adminName2/>
<alternateName lang="link">http://en.wikipedia.org/wiki/Norton%2C_Zimbabwe</alternateName>
<alternateName lang="ru">Нортон</alternateName>
<timezone dstOffset="2.0" gmtOffset="2.0">Africa/Harare</timezone>
<bbox>
<west>30.66902</west>
<north>-17.85385</north>
<east>30.73098</east>
<south>-17.91282</south>
</bbox>
<score>13.51087474822998</score>
</geoname>
<geoname>
<toponymName>Norton</toponymName>
<name>Norton</name>
<lat>41.02922</lat>
<lng>-81.63818</lng>
<geonameId>5165087</geonameId>
<countryCode>US</countryCode>
<countryName>United States</countryName>
<fcl>P</fcl>
<fcode>PPL</fcode>
<fclName>city, village,...</fclName>
<fcodeName>populated place</fcodeName>
<population>12085</population>
<alternateNames/>
<elevation>325</elevation>
<continentCode>NA</continentCode>
<adminCode1 ISO3166-2="OH">OH</adminCode1>
<adminName1>Ohio</adminName1>
<adminCode2>153</adminCode2>
<adminName2>Summit County</adminName2>
<alternateName lang="link">http://en.wikipedia.org/wiki/Norton%2C_Ohio</alternateName>
<timezone dstOffset="-4.0" gmtOffset="-5.0">America/New_York</timezone>
<bbox>
<west>-81.68849</west>
<north>41.06255</north>
<east>-81.58882</east>
<south>40.9823</south>
</bbox>
<score>9.553630828857422</score>
</geoname>
<geoname>
<toponymName>Norton</toponymName>
<name>Norton</name>
<lat>52.26667</lat>
<lng>-1.11667</lng>
<geonameId>2641203</geonameId>
<countryCode>GB</countryCode>
<countryName>United Kingdom</countryName>
<fcl>P</fcl>
<fcode>PPL</fcode>
<fclName>city, village,...</fclName>
<fcodeName>populated place</fcodeName>
<population/>
<alternateNames>Norton</alternateNames>
<elevation/>
<continentCode>EU</continentCode>
<adminCode1 ISO3166-2="ENG">ENG</adminCode1>
<adminName1>England</adminName1>
<adminCode2>J1</adminCode2>
<adminName2>Northamptonshire</adminName2>
<adminCode3>34UC</adminCode3>
<adminName3>Daventry District</adminName3>
<alternateName lang="link">http://en.wikipedia.org/wiki/Norton%2C_Northamptonshire</alternateName>
<timezone dstOffset="1.0" gmtOffset="0.0">Europe/London</timezone>
<bbox>
<west>-1.13137</west>
<north>52.27566</north>
<east>-1.10197</east>
<south>52.25767</south>
</bbox>
<score>8.7755708694458</score>
</geoname>
<geoname>
<toponymName>Norton</toponymName>
<name>Norton</name>
<lat>52.25</lat>
<lng>0.86667</lng>
<geonameId>2641204</geonameId>
<countryCode>GB</countryCode>
<countryName>United Kingdom</countryName>
<fcl>P</fcl>
<fcode>PPL</fcode>
<fclName>city, village,...</fclName>
<fcodeName>populated place</fcodeName>
<population/>
<alternateNames>Norton</alternateNames>
<elevation/>
<continentCode>EU</continentCode>
<adminCode1 ISO3166-2="ENG">ENG</adminCode1>
<adminName1>England</adminName1>
<adminCode2>N5</adminCode2>
<adminName2>Suffolk</adminName2>
<adminCode3>42UE</adminCode3>
<adminName3>Mid Suffolk District</adminName3>
<alternateName lang="link">http://en.wikipedia.org/wiki/Norton%2C_Suffolk</alternateName>
<timezone dstOffset="1.0" gmtOffset="0.0">Europe/London</timezone>
<bbox>
<west>0.85197</west>
<north>52.25899</north>
<east>0.88136</east>
<south>52.24101</south>
</bbox>
<score>8.7755708694458</score>
</geoname>
<geoname>
<toponymName>Norton</toponymName>
<name>Norton</name>
<lat>41.96677</lat>
<lng>-71.18699</lng>
<geonameId>4945911</geonameId>
<countryCode>US</countryCode>
<countryName>United States</countryName>
<fcl>P</fcl>
<fcode>PPL</fcode>
<fclName>city, village,...</fclName>
<fcodeName>populated place</fcodeName>
<population>19808</population>
<alternateNames/>
<elevation>32</elevation>
<continentCode>NA</continentCode>
<adminCode1 ISO3166-2="MA">MA</adminCode1>
<adminName1>Massachusetts</adminName1>
<adminCode2>005</adminCode2>
<adminName2>Bristol County</adminName2>
<alternateName lang="link">http://en.wikipedia.org/wiki/Norton%2C_Massachusetts</alternateName>
<alternateName lang="post">02766</alternateName>
<alternateName lang="unlc">NNM</alternateName>
<timezone dstOffset="-4.0" gmtOffset="-5.0">America/New_York</timezone>
<bbox>
<west>-71.21119</west>
<north>41.98475</north>
<east>-71.1628</east>
<south>41.94878</south>
</bbox>
<score>8.359426498413086</score>
</geoname>
<geoname>
<toponymName>Norton</toponymName>
<name>Norton</name>
<lat>52.20705</lat>
<lng>-2.48085</lng>
<geonameId>7294526</geonameId>
<countryCode>GB</countryCode>
<countryName>United Kingdom</countryName>
<fcl>A</fcl>
<fcode>ADM3</fcode>
<fclName>country, state, region,...</fclName>
<fcodeName>third-order administrative division</fcodeName>
<population/>
<alternateNames/>
<elevation/>
<continentCode>EU</continentCode>
<adminCode1 ISO3166-2="ENG">ENG</adminCode1>
<adminName1>England</adminName1>
<adminCode2>F7</adminCode2>
<adminName2>Herefordshire</adminName2>
<adminCode3>00GA162</adminCode3>
<adminName3>Norton</adminName3>
<timezone dstOffset="1.0" gmtOffset="0.0">Europe/London</timezone>
<bbox>
<west>-2.5059</west>
<north>52.22545</north>
<east>-2.45579</east>
<south>52.18866</south>
</bbox>
<score>8.359426498413086</score>
</geoname>
<geoname>
<toponymName>Norton</toponymName>
<name>Norton</name>
<lat>53.62165</lat>
<lng>-1.18327</lng>
<geonameId>7297773</geonameId>
<countryCode>GB</countryCode>
<countryName>United Kingdom</countryName>
<fcl>A</fcl>
<fcode>ADM3</fcode>
<fclName>country, state, region,...</fclName>
<fcodeName>third-order administrative division</fcodeName>
<population/>
<alternateNames/>
<elevation/>
<continentCode>EU</continentCode>
<adminCode1 ISO3166-2="ENG">ENG</adminCode1>
<adminName1>England</adminName1>
<adminCode2>D5</adminCode2>
<adminName2>Doncaster</adminName2>
<adminCode3>00CE032</adminCode3>
<adminName3>Norton</adminName3>
<timezone dstOffset="1.0" gmtOffset="0.0">Europe/London</timezone>
<bbox>
<west>-1.23284</west>
<north>53.64345</north>
<east>-1.1337</east>
<south>53.59985</south>
</bbox>
<score>8.359426498413086</score>
</geoname>
<geoname>
<toponymName>Norton</toponymName>
<name>Norton</name>
<lat>51.56503</lat>
<lng>-2.15578</lng>
<geonameId>7300356</geonameId>
<countryCode>GB</countryCode>
<countryName>United Kingdom</countryName>
<fcl>A</fcl>
<fcode>ADM3</fcode>
<fclName>country, state, region,...</fclName>
<fcodeName>third-order administrative division</fcodeName>
<population/>
<alternateNames/>
<elevation/>
<continentCode>EU</continentCode>
<adminCode1 ISO3166-2="ENG">ENG</adminCode1>
<adminName1>England</adminName1>
<adminCode2>P8</adminCode2>
<adminName2>Wiltshire</adminName2>
<adminCode3>00HY171</adminCode3>
<adminName3>Norton</adminName3>
<timezone dstOffset="1.0" gmtOffset="0.0">Europe/London</timezone>
<bbox>
<west>-2.1898</west>
<north>51.58276</north>
<east>-2.12176</east>
<south>51.54729</south>
</bbox>
<score>8.359426498413086</score>
</geoname>
<geoname>
<toponymName>Norton</toponymName>
<name>Norton</name>
<lat>51.99442</lat>
<lng>-0.20844</lng>
<geonameId>2641205</geonameId>
<countryCode>GB</countryCode>
<countryName>United Kingdom</countryName>
<fcl>P</fcl>
<fcode>PPL</fcode>
<fclName>city, village,...</fclName>
<fcodeName>populated place</fcodeName>
<population/>
<alternateNames/>
<elevation/>
<continentCode>EU</continentCode>
<adminCode1 ISO3166-2="ENG">ENG</adminCode1>
<adminName1>England</adminName1>
<adminCode2>F8</adminCode2>
<adminName2>Hertfordshire</adminName2>
<adminCode3>26UF</adminCode3>
<adminName3>North Hertfordshire District</adminName3>
<alternateName lang="link">http://en.wikipedia.org/wiki/Norton%2C_Hertfordshire</alternateName>
<timezone dstOffset="1.0" gmtOffset="0.0">Europe/London</timezone>
<bbox>
<west>-0.22305</west>
<north>52.00341</north>
<east>-0.19383</east>
<south>51.98543</south>
</bbox>
<score>7.165223121643066</score>
</geoname>
</geonames>
