<?xml version="1.0" encoding="UTF-8" standalone="no"?>
<geonames style="FULL">
<totalResultsCount>46</totalResultsCount>
<geoname>
<toponymName>Richland</toponymName>
<name>Richland</name>
<lat>46.28569</lat>
<lng>-119.28446</lng>
<geonameId>5808276</geonameId>
<countryCode>US</countryCode>
<countryName>United States</countryName>
<fcl>P</fcl>
<fcode>PPL</fcode>
<fclName>city, village,...</fclName>
<fcodeName>populated place</fcodeName>
<population>48058</population>
<alternateNames>Richland,Richlend,li qi lan,ritchirando,rych lnd, washyngtn,rytshland, washntn,ryz'lnd,Ричланд,Ричленд,ריצ'לנד,ريتشلاند، واشنطن,ریچ لند، واشینگتن,リッチランド,里奇兰</alternateNames>
<elevation>117</elevation>
<continentCode>NA</continentCode>
<adminCode1 ISO3166-2="WA">WA</adminCode1>
<adminName1>Washington</adminName1>
<adminCode2>005</adminCode2>
<adminName2>Benton County</adminName2>
<alternateName lang="ar">ريتشلاند، واشنطن</alternateName>
<alternateName lang="bg">Ричланд</alternateName>
<alternateName lang="fa">ریچ لند، واشینگتن</alternateName>
<alternateName lang="he">ריצ'לנד</alternateName>
<alternateName lang="ja">リッチランド</alternateName>
<alternateName lang="link">http://en.wikipedia.org/wiki/Richland%2C_Washington</alternateName>
<alternateName lang="post">99352</alternateName>
<alternateName lang="ru">Ричланд</alternateName>
<alternateName lang="sr">Ричланд</alternateName>
<alternateName lang="zh">里奇兰</alternateName>
<timezone dstOffset="-7.0" gmtOffset="-8.0">America/Los_Angeles</timezone>
<bbox>
<west>-119.32564</west>
<north>46.31413</north>
<east>-119.24329</east>
<south>46.25725</south>
</bbox>
<score>36.18781661987305</score>
</geoname>
<geoname>
<toponymName>Richland</toponymName>
<name>Richland</name>
<lat>39.49755</lat>
<lng>-85.39497</lng>
<geonameId>4263665</geonameId>
<countryCode>US</countryCode>
<countryName>United States</countryName>
<fcl>P</fcl>
<fcode>PPL</fcode>
<fclName>city, village,...</fclName>
<fcodeName>populated place</fcodeName>
<population/>
<alternateNames/>
<elevation>312</elevation>
<continentCode>NA</continentCode>
<adminCode1 ISO3166-2="IN">IN</adminCode1>
<adminName1>Indiana</adminName1>
<adminCode2>139</adminCode2>
<adminName2>Rush County</adminName2>
<alternateName lang="link">http://en.wikipedia.org/wiki/Richland%2C_Indiana</alternateName>
<timezone dstOffset="-4.0" gmtOffset="-5.0">America/Indiana/Indianapolis</timezone>
<bbox>
<west>-85.40662</west>
<north>39.50654</north>
<east>-85.38331</east>
<south>39.48855</south>
</bbox>
<score>31.339569091796875</score>
</geoname>
<geoname>
<toponymName>Richland</toponymName>
<name>Richland</name>
<lat>38.88361</lat>
<lng>-95.5397</lng>
<geonameId>4278007</geonameId>
<countryCode>US</countryCode>
<countryName>United States</countryName>
<fcl>P</fcl>
<fcode>PPL</fcode>
<fclName>city, village,...</fclName>
<fcodeName>populated place</fcodeName>
<population/>
<alternateNames/>
<elevation>285</elevation>
<continentCode>NA</continentCode>
<adminCode1 ISO3166-2="KS">KS</adminCode1>
<adminName1>Kansas</adminName1>
<adminCode2>177</adminCode2>
<adminName2>Shawnee County</adminName2>
<alternateName lang="link">http://en.wikipedia.org/wiki/Richland%2C_Kansas</alternateName>
<timezone dstOffset="-5.0" gmtOffset="-6.0">America/Chicago</timezone>
<bbox>
<west>-95.55126</west>
<north>38.89261</north>
<east>-95.52815</east>
<south>38.87462</south>
</bbox>
<score>31.339569091796875</score>
</geoname>
<geoname>
<toponymName>Richland</toponymName>
<name>Richland</name>
<lat>32.9743</lat>
<lng>-89.98647</lng>
<geonameId>4443257</geonameId>
<countryCode>US</countryCode>
<countryName>United States</countryName>
<fcl>P</fcl>
<fcode>PPL</fcode>
<fclName>city, village,...</fclName>
<fcodeName>populated place</fcodeName>
<population/>
<alternateNames/>
<elevation>99</elevation>
<continentCode>NA</continentCode>
<adminCode1 ISO3166-2="MS">MS</adminCode1>
<adminName1>Mississippi</adminName1>
<adminCode2>051</adminCode2>
<adminName2>Holmes County</adminName2>
<alternateName lang="link">http://en.wikipedia.org/wiki/Richland%2C_Holmes_County%2C_Mississippi</alternateName>
<timezone dstOffset="-5.0" gmtOffset="-6.0">America/Chicago</timezone>
<bbox>
<west>-89.9972</west>
<north>32.98329</north>
<east>-89.97575</east>
<south>32.9653</south>
</bbox>
<score>31.339569091796875</score>
</geoname>
<geoname>
<toponymName>Richland</toponymName>
<name>Richland</name>
<lat>39.49178</lat>
<lng>-74.87072</lng>
<geonameId>4503779</geonameId>
<countryCode>US</countryCode>
<countryName>United States</countryName>
<fcl>P</fcl>
<fcode>PPL</fcode>
<fclName>city, village,...</fclName>
<fcodeName>populated place</fcodeName>
<population/>
<alternateNames/>
<elevation>29</elevation>
<continentCode>NA</continentCode>
<adminCode1 ISO3166-2="NJ">NJ</adminCode1>
<adminName1>New Jersey</adminName1>
<adminCode2>001</adminCode2>
<adminName2>Atlantic County</adminName2>
<alternateName lang="link">http://en.wikipedia.org/wiki/Richland%2C_New_Jersey</alternateName>
<alternateName lang="post">08350</alternateName>
<timezone dstOffset="-4.0" gmtOffset="-5.0">America/New_York</timezone>
<bbox>
<west>-74.88238</west>
<north>39.50078</north>
<east>-74.85907</east>
<south>39.48279</south>
</bbox>
<score>31.339569091796875</score>
</geoname>
<geoname>
<toponymName>Richland</toponymName>
<name>Richland</name>
<lat>43.56951</lat>
<lng>-76.0477</lng>
<geonameId>5133799</geonameId>
<countryCode>US</countryCode>
<countryName>United States</countryName>
<fcl>P</fcl>
<fcode>PPL</fcode>
<fclName>city, village,...</fclName>
<fcodeName>populated place</fcodeName>
<population/>
<alternateNames/>
<elevation>166</elevation>
<continentCode>NA</continentCode>
<adminCode1 ISO3166-2="NY">NY</adminCode1>
<adminName1>New York</adminName1>
<adminCode2>075</adminCode2>
<adminName2>Oswego County</adminName2>
<alternateName lang="link">http://en.wikipedia.org/wiki/Richland%2C_New_York</alternateName>
<alternateName lang="post">13144</alternateName>
<timezone dstOffset="-4.0" gmtOffset="-5.0">America/New_York</timezone>
<bbox>
<west>-76.06011</west>
<north>43.57851</north>
<east>-76.03528</east>
<south>43.56052</south>
</bbox>
<score>31.339569091796875</score>
</geoname>
<geoname>
<toponymName>Richland</toponymName>
<name>Richland</name>
<lat>42.75944</lat>
<lng>-96.65281</lng>
<geonameId>5230814</geonameId>
<countryCode>US</countryCode>
<countryName>United States</countryName>
<fcl>P</fcl>
<fcode>PPL</fcode>
<fclName>city, village,...</fclName>
<fcodeName>populated place</fcodeName>
<population>89</population>
<alternateNames/>
<elevation>344</elevation>
<continentCode>NA</continentCode>
<adminCode1 ISO3166-2="SD">SD</adminCode1>
<adminName1>South Dakota</adminName1>
<adminCode2>127</adminCode2>
<adminName2>Union County</adminName2>
<alternateName lang="link">http://en.wikipedia.org/wiki/Richland%2C_South_Dakota</alternateName>
<timezone dstOffset="-5.0" gmtOffset="-6.0">America/Chicago</timezone>
<bbox>
<west>-96.65404</west>
<north>42.76034</north>
<east>-96.65159</east>
<south>42.75854</south>
</bbox>
<score>31.339569091796875</score>
</geoname>
<geoname>
<toponymName>Richland</toponymName>
<name>Richland</name>
<lat>32.08793</lat>
<lng>-84.66742</lng>
<geonameId>4218732</geonameId>
<countryCode>US</countryCode>
<countryName>United States</countryName>
<fcl>P</fcl>
<fcode>PPL</fcode>
<fclName>city, village,...</fclName>
<fcodeName>populated place</fcodeName>
<population>1473</population>
<alternateNames>Richlend,Ричленд</alternateNames>
<elevation>185</elevation>
<continentCode>NA</continentCode>
<adminCode1 ISO3166-2="GA">GA</adminCode1>
<adminName1>Georgia</adminName1>
<adminCode2>259</adminCode2>
<adminName2>Stewart County</adminName2>
<alternateName lang="link">http://en.wikipedia.org/wiki/Richland%2C_Georgia</alternateName>
<alternateName lang="post">31825</alternateName>
<alternateName lang="ru">Ричленд</alternateName>
<timezone dstOffset="-4.0" gmtOffset="-5.0">America/New_York</timezone>
<bbox>
<west>-84.67273</west>
<north>32.09243</north>
<east>-84.66211</east>
<south>32.08344</south>
</bbox>
<score>26.11630630493164</score>
</geoname>
<geoname>
<toponymName>Richland</toponymName>
<name>Richland</name>
<lat>37.85698</lat>
<lng>-92.40434</lng>
<geonameId>4405558</geonameId>
<countryCode>US</countryCode>
<countryName>United States</countryName>
<fcl>P</fcl>
<fcode>PPL</fcode>
<fclName>city, village,...</fclName>
<fcodeName>populated place</fcodeName>
<population>1863</population>
<alternateNames>Richlend,Ричленд</alternateNames>
<elevation>346</elevation>
<continentCode>NA</continentCode>
<adminCode1 ISO3166-2="MO">MO</adminCode1>
<adminName1>Missouri</adminName1>
<adminCode2>169</adminCode2>
<adminName2>Pulaski County</adminName2>
<alternateName lang="link">http://en.wikipedia.org/wiki/Richland%2C_Missouri</alternateName>
<alternateName lang="post">65556</alternateName>
<alternateName lang="ru">Ричленд</alternateName>
<alternateName lang="unlc">RRM</alternateName>
<timezone dstOffset="-5.0" gmtOffset="-6.0">America/Chicago</timezone>
<bbox>
<west>-92.41004</west>
<north>37.86148</north>
<east>-92.39864</east>
<south>37.85249</south>
</bbox>
<score>26.11630630493164</score>
</geoname>
<geoname>
<toponymName>Richland</toponymName>
<name>Richland</name>
<lat>32.23904</lat>
<lng>-90.15842</lng>
<geonameId>4443249</geonameId>
<countryCode>US</countryCode>
<countryName>United States</countryName>
<fcl>P</fcl>
<fcode>PPL</fcode>
<fclName>city, village,...</fclName>
<fcodeName>populated place</fcodeName>
<population>6912</population>
<alternateNames>Richlend,Ричленд</alternateNames>
<elevation>81</elevation>
<continentCode>NA</continentCode>
<adminCode1 ISO3166-2="MS">MS</adminCode1>
<adminName1>Mississippi</adminName1>
<adminCode2>121</adminCode2>
<adminName2>Rankin County</adminName2>
<alternateName lang="link">http://en.wikipedia.org/wiki/Richland%2C_Mississippi</alternateName>
<alternateName lang="post">39218</alternateName>
<alternateName lang="ru">Ричленд</alternateName>
<timezone dstOffset="-5.0" gmtOffset="-6.0">America/Chicago</timezone>
<bbox>
<west>-90.17031</west>
<north>32.24909</north>
<east>-90.14653</east>
<south>32.22898</south>
</bbox>
<score>26.11630630493164</score>
</geoname>
</geonames>
